dq_gpu/__init__.py
dq_gpu/_version.py
dq_gpu/handlers.py
dq_gpu/websocket.py
dq_gpu/tests/__init__.py
dq_gpu/tests/test_handlers.py
dq_gpu-0.1.0.data/data/etc/jupyter/jupyter_server_config.d/dq_gpu.json
dq_gpu-0.1.0.data/data/share/jupyter/labextensions/dq-gpu/package.json
dq_gpu-0.1.0.data/data/share/jupyter/labextensions/dq-gpu/schemas/dq-gpu/package.json.orig
dq_gpu-0.1.0.data/data/share/jupyter/labextensions/dq-gpu/schemas/dq-gpu/plugin.json
dq_gpu-0.1.0.data/data/share/jupyter/labextensions/dq-gpu/static/394.47f9e39cb3c82d3f6172.js
dq_gpu-0.1.0.data/data/share/jupyter/labextensions/dq-gpu/static/763.a4026b6a566b54887eca.js
dq_gpu-0.1.0.data/data/share/jupyter/labextensions/dq-gpu/static/remoteEntry.51c5b03f1a054f6fee46.js
dq_gpu-0.1.0.data/data/share/jupyter/labextensions/dq-gpu/static/style.js
dq_gpu-0.1.0.data/data/share/jupyter/labextensions/dq-gpu/static/third-party-licenses.json
dq_gpu-0.1.0.data/data/share/jupyter/labextensions/dq-gpu/install.json
dq_gpu-0.1.0.dist-info/METADATA
dq_gpu-0.1.0.dist-info/WHEEL
dq_gpu-0.1.0.dist-info/licenses/LICENSE
dq_gpu-0.1.0.dist-info/RECORD
